tini.py
tini-3.0.1.dist-info/DESCRIPTION.rst
tini-3.0.1.dist-info/METADATA
tini-3.0.1.dist-info/metadata.json
tini-3.0.1.dist-info/RECORD
tini-3.0.1.dist-info/top_level.txt
tini-3.0.1.dist-info/WHEEL
