Metadata-Version: 1.1
Name: tini
Version: 3.0.1
Summary: Read simple .ini/configuration files.
Home-page: https://github.com/beaugunderson/python-tini
Author: Beau Gunderson
Author-email: beau@beaugunderson.com
License: MIT
Keywords: config,configuration,ini
Platform: UNKNOWN
Classifier: Development Status :: 5 - Production/Stable
Classifier: Intended Audience :: Developers
Classifier: License :: OSI Approved :: MIT License
Classifier: Operating System :: POSIX
Classifier: Operating System :: Microsoft :: Windows
Classifier: Operating System :: MacOS :: MacOS X
Classifier: Topic :: Software Development :: Libraries
Classifier: Topic :: Utilities
Classifier: Programming Language :: Python :: 2
Classifier: Programming Language :: Python :: 2.7
Classifier: Programming Language :: Python :: 3
Classifier: Programming Language :: Python :: 3.4
